ml_indie_tools/ALU_Dataset.py
ml_indie_tools/Calibre_Dataset.py
ml_indie_tools/Folder_Dataset.py
ml_indie_tools/Gutenberg_Dataset.py
ml_indie_tools/Text_Dataset.py
ml_indie_tools/__init__.py
ml_indie_tools/env_tools.py
ml_indie_tools/pytorch_custom_layers.py
ml_indie_tools/pytorch_meta_tools.py
ml_indie_tools/pytorch_tr_compr_layers.py
ml_indie_tools/train_utils.py
ml_indie_tools/tuner.py
ml_indie_tools-0.13.1.dist-info/LICENSE
ml_indie_tools-0.13.1.dist-info/METADATA
ml_indie_tools-0.13.1.dist-info/WHEEL
ml_indie_tools-0.13.1.dist-info/top_level.txt
ml_indie_tools-0.13.1.dist-info/RECORD
