Metadata-Version: 2.2
Name: ml-indie-tools
Version: 0.13.1
Summary: A collection of tools for low-resource indie machine learning development
Author-email: Dominik Schlösser <dominik.schloesser@gmail.com>
Classifier: Programming Language :: Python :: 3
Classifier: License :: OSI Approved :: MIT License
Classifier: Operating System :: OS Independent
Requires-Python: >=3.12
License-File: LICENSE
